{
  "phone": {
    "image": {
      "I1": 16,
      "I2": 20,
      "I3": 24,
      "I4": 32,
      "I5": 40,
      "I6": 56,
      "I7": 64
    },
    "padding": {
      "P0": 0,
      "P1": 4,
      "P2": 8,
      "P3": 12,
      "P4": 16,
      "P5": 20,
      "P6": 24,
      "P7": 28,
      "P8": 32,
      "P9": 40
    },
    "circle": {
      "C1_1": 8,
      "C1_2": 6,
      "C1_3": 4,
      "C2": 16,
      "C2_2": 24,
      "C2_3": 32,
      "C3_1": 16,
      "C3_2": 12,
      "C3_3": 8,
      "C3_4": 4
    },
    "new_circle": {
      "straight": {
        "C1_1": 4,
        "C1_2": 4,
        "C1_3": 4,
        "C2": 4,
        "C2_2": 4,
        "C2_3": 4,
        "C3_1": 4,
        "C3_2": 4,
        "C3_3": 4,
        "C3_4": 4
      },
      "angle": {
        "C1_1": 8,
        "C1_2": 6,
        "C1_3": 4,
        "C2": 16,
        "C2_2": 24,
        "C2_3": 32,
        "C3_1": 16,
        "C3_2": 12,
        "C3_3": 8,
        "C3_4": 4
      },
      "pure_straight": {
        "C1_1": 0,
        "C1_2": 0,
        "C1_3": 0,
        "C2": 0,
        "C2_2": 0,
        "C2_3": 0,
        "C3_1": 0,
        "C3_2": 0,
        "C3_3": 0,
        "C3_4": 0
      },
      "large_angle": {
        "C1_1": 24,
        "C1_2": 18,
        "C1_3": 15,
        "C2": 16,
        "C2_2": 24,
        "C2_3": 32,
        "C3_1": 16,
        "C3_2": 12,
        "C3_3": 8,
        "C3_4": 4
      }
    },
    "iconfont": {
      "IC1": 16,
      "IC2": 20,
      "IC3": 24,
      "IC4": 32,
      "IC5": 40,
      "IC6": 56
    },
    "text": {
      "T1": {
        "f": 11,
        "p": 1,
        "h": 16
      },
      "T2": {
        "f": 12,
        "p": 2,
        "h": 16
      },
      "T3": {
        "f": 13,
        "p": 1,
        "h": 20
      },
      "T4": {
        "f": 14,
        "p": 2,
        "h": 20
      },
      "T5": {
        "f": 15,
        "p": 3,
        "h": 20
      },
      "T6": {
        "f": 16,
        "p": 4,
        "h": 24
      },
      "T7": {
        "f": 17,
        "p": 3,
        "h": 24
      },
      "T8": {
        "f": 18,
        "p": 4,
        "h": 28
      },
      "T9": {
        "f": 20,
        "p": 4,
        "h": 32
      },
      "T10": {
        "f": 22,
        "p": 4,
        "h": 36
      },
      "T11": {
        "f": 24,
        "p": 4,
        "h": 36
      },
      "T12": {
        "f": 28,
        "p": 6,
        "h": 48
      },
      "T13": {
        "f": 32,
        "p": 6,
        "h": 56
      }
    }
  },
  "pad": {
    "image": {
      "I1": 20,
      "I2": 24,
      "I3": 32,
      "I4": 40,
      "I5": 56,
      "I6": 64,
      "I7": 80
    },
    "padding": {
      "P0": 0,
      "P1": 8,
      "P2": 12,
      "P3": 20,
      "P4": 24,
      "P5": 28,
      "P6": 32,
      "P7": 36,
      "P8": 40,
      "P9": 56
    },
    "circle": {
      "C1_1": 12,
      "C1_2": 8,
      "C1_3": 6,
      "C2": 20,
      "C2_2": 32,
      "C2_3": 32,
      "C3_1": 20,
      "C3_2": 16,
      "C3_3": 12,
      "C3_4": 8
    },
    "new_circle": {
      "straight": {
        "C1_1": 8,
        "C1_2": 8,
        "C1_3": 8,
        "C2": 8,
        "C2_2": 8,
        "C2_3": 8,
        "C3_1": 8,
        "C3_2": 8,
        "C3_3": 8,
        "C3_4": 8
      },
      "angle": {
        "C1_1": 12,
        "C1_2": 8,
        "C1_3": 6,
        "C2": 20,
        "C2_2": 32,
        "C2_3": 32,
        "C3_1": 20,
        "C3_2": 16,
        "C3_3": 12,
        "C3_4": 8
      },
      "pure_straight": {
        "C1_1": 0,
        "C1_2": 0,
        "C1_3": 0,
        "C2": 0,
        "C2_2": 0,
        "C2_3": 0,
        "C3_1": 0,
        "C3_2": 0,
        "C3_3": 0,
        "C3_4": 0
      },
      "large_angle": {
        "C1_1": 26,
        "C1_2": 20,
        "C1_3": 17,
        "C2": 20,
        "C2_2": 32,
        "C2_3": 32,
        "C3_1": 20,
        "C3_2": 16,
        "C3_3": 12,
        "C3_4": 8
      }
    },
    "iconfont": {
      "IC1": 20,
      "IC2": 24,
      "IC3": 32,
      "IC4": 40,
      "IC5": 56,
      "IC6": 64
    },
    "text": {
      "T1": {
        "f": 13,
        "p": 1,
        "h": 20
      },
      "T2": {
        "f": 14,
        "p": 2,
        "h": 20
      },
      "T3": {
        "f": 15,
        "p": 3,
        "h": 20
      },
      "T4": {
        "f": 16,
        "p": 4,
        "h": 24
      },
      "T5": {
        "f": 17,
        "p": 3,
        "h": 24
      },
      "T6": {
        "f": 18,
        "p": 4,
        "h": 28
      },
      "T7": {
        "f": 20,
        "p": 4,
        "h": 28
      },
      "T8": {
        "f": 22,
        "p": 4,
        "h": 36
      },
      "T9": {
        "f": 24,
        "p": 6,
        "h": 36
      },
      "T10": {
        "f": 26,
        "p": 6,
        "h": 44
      },
      "T11": {
        "f": 28,
        "p": 6,
        "h": 48
      },
      "T12": {
        "f": 32,
        "p": 6,
        "h": 56
      },
      "T13": {
        "f": 40,
        "p": 8,
        "h": 64
      }
    }
  }
}
